model_ultils_library/__init__.py
model_ultils_library/main.py
model_utils_ai-3.2.0.dist-info/METADATA
model_utils_ai-3.2.0.dist-info/WHEEL
model_utils_ai-3.2.0.dist-info/top_level.txt
model_utils_ai-3.2.0.dist-info/RECORD
